setup.py
galileopy/__init__.py
galileopy.egg-info/PKG-INFO
galileopy.egg-info/SOURCES.txt
galileopy.egg-info/dependency_links.txt
galileopy.egg-info/not-zip-safe
galileopy.egg-info/top_level.txt