Metadata-Version: 1.2
Name: galileopy
Version: 0.1
Summary: A package for downloading, reading, and creating summary plots of the Galileo Orbiter mission data available on NASA PDS.
Home-page: https://github.com/cdkharris/galileopy.git
Author: Camilla D. K. Harris
Author-email: cdha@umich.edu
License: MIT
Platform: UNKNOWN
Requires-Python: >=3
